telegram_mcp_bot/__init__.py
telegram_mcp_bot/agent_runner.py
telegram_mcp_bot/agent_runner_browser_only.py
telegram_mcp_bot/cli.py
telegram_mcp_bot/personal_assistant.py
telegram_mcp_bot/telegram_collector_direct.py
telegram_mcp_bot/telegram_collector_natural.py
telegram_mcp_bot/utils/__init__.py
telegram_mcp_bot/utils/check_metadata.py
telegram_mcp_bot/utils/check_status.py
telegram_mcp_bot-1.0.0.dist-info/METADATA
telegram_mcp_bot-1.0.0.dist-info/WHEEL
telegram_mcp_bot-1.0.0.dist-info/entry_points.txt
telegram_mcp_bot-1.0.0.dist-info/licenses/LICENSE
telegram_mcp_bot-1.0.0.dist-info/RECORD
