Metadata-Version: 2.4
Name: telegram-mcp-bot
Version: 1.0.0
Summary: Unified Telegram bot with MCP (Model Context Protocol) for information collection and RAG assistant
Project-URL: Homepage, https://github.com/trashchenkov/unified-telegram-mcp-bot
Project-URL: Repository, https://github.com/trashchenkov/unified-telegram-mcp-bot.git
Project-URL: Issues, https://github.com/trashchenkov/unified-telegram-mcp-bot/issues
Project-URL: Documentation, https://github.com/trashchenkov/unified-telegram-mcp-bot#readme
Author-email: Sergei Trashchenkov <trashchenkov@gmail.com>
License: MIT
License-File: LICENSE
Keywords: ai,bot,chromadb,llm,mcp,rag,telegram
Classifier: Development Status :: 4 - Beta
Classifier: Intended Audience :: Developers
Classifier: License :: OSI Approved :: MIT License
Classifier: Programming Language :: Python :: 3
Classifier: Programming Language :: Python :: 3.11
Classifier: Programming Language :: Python :: 3.12
Classifier: Topic :: Communications :: Chat
Classifier: Topic :: Scientific/Engineering :: Artificial Intelligence
Requires-Python: >=3.11
Requires-Dist: aiofiles>=24.1.0
Requires-Dist: aiogram>=3.15.0
Requires-Dist: aiohttp>=3.11.10
Requires-Dist: aiosqlite>=0.20.0
Requires-Dist: asyncio-mqtt>=0.16.2
Requires-Dist: chromadb>=0.5.23
Requires-Dist: httpx>=0.28.1
Requires-Dist: langchain-gigachat>=0.3.2
Requires-Dist: langchain-openai>=0.2.11
Requires-Dist: langchain>=0.3.12
Requires-Dist: langgraph>=0.2.49
Requires-Dist: playwright>=1.48.0
Requires-Dist: python-dotenv>=1.0.1
Requires-Dist: sqlalchemy>=2.0.36
Provides-Extra: dev
Requires-Dist: black>=24.0.0; extra == 'dev'
Requires-Dist: isort>=5.13.0; extra == 'dev'
Requires-Dist: mypy>=1.8.0; extra == 'dev'
Requires-Dist: pytest-asyncio>=0.24.0; extra == 'dev'
Requires-Dist: pytest>=8.0.0; extra == 'dev'
